wrapper/Process.cpython-310-x86_64-linux-gnu.so
wrapper/__init__.py
wrapper/core/DocumentSearch.cpython-310-x86_64-linux-gnu.so
wrapper/core/DocumentSearchSB.cpython-310-x86_64-linux-gnu.so
wrapper/core/DocumentSearchTD.cpython-310-x86_64-linux-gnu.so
wrapper/core/File.cpython-310-x86_64-linux-gnu.so
wrapper/core/Image.cpython-310-x86_64-linux-gnu.so
wrapper/core/PDF.cpython-310-x86_64-linux-gnu.so
wrapper/core/SentenceTransformerVectorizer.cpython-310-x86_64-linux-gnu.so
wrapper/core/Vectorizer.cpython-310-x86_64-linux-gnu.so
wrapper/core/Video.cpython-310-x86_64-linux-gnu.so
wrapper/core/__init__.py
wrapper/infra/AbsctractGenerator.cpython-310-x86_64-linux-gnu.so
wrapper/infra/DocLanguage.cpython-310-x86_64-linux-gnu.so
wrapper/infra/ImageObjectsExtractor.cpython-310-x86_64-linux-gnu.so
wrapper/infra/LanguageDetector.cpython-310-x86_64-linux-gnu.so
wrapper/infra/ModelType.cpython-310-x86_64-linux-gnu.so
wrapper/infra/NERExtractor.cpython-310-x86_64-linux-gnu.so
wrapper/infra/PreProcessing.cpython-310-x86_64-linux-gnu.so
wrapper/infra/TextExtractor.cpython-310-x86_64-linux-gnu.so
wrapper/infra/VideoObjectsExtractor.cpython-310-x86_64-linux-gnu.so
wrapper/infra/WordFixer.cpython-310-x86_64-linux-gnu.so
wrapper/infra/__init__.py
wrapper/infra/res/__init__.py
docrx-0.0.114.dist-info/LICENSE.txt
docrx-0.0.114.dist-info/METADATA
docrx-0.0.114.dist-info/WHEEL
docrx-0.0.114.dist-info/top_level.txt
docrx-0.0.114.dist-info/RECORD
