Metadata-Version: 2.1
Name: docrx
Version: 0.0.114
Summary: search in documents
Home-page: UNKNOWN
Author: Tiago Zamperini
Author-email: tiagozamperini@live.com
License: MIT
Platform: UNKNOWN
Classifier: Development Status :: 1 - Planning
Classifier: License :: OSI Approved :: MIT License
Classifier: Intended Audience :: Education
Classifier: Intended Audience :: Science/Research
Classifier: Topic :: Scientific/Engineering
Classifier: Topic :: Scientific/Engineering :: Mathematics
Classifier: Natural Language :: English
Classifier: Operating System :: OS Independent
Classifier: Programming Language :: C
Classifier: Programming Language :: Cython
Classifier: Programming Language :: Python
Classifier: Programming Language :: Python :: 3
Classifier: Programming Language :: Python :: 3.4
Classifier: Programming Language :: Python :: 3.5
Classifier: Programming Language :: Python :: 3.6
Classifier: Programming Language :: Python :: 3.7
Classifier: Programming Language :: Python :: 3.8
Classifier: Programming Language :: Python :: 3.9
Classifier: Programming Language :: Python :: 3.10
Classifier: Programming Language :: Python :: 3 :: Only
Classifier: Programming Language :: Python :: Implementation :: CPython
Requires-Python: >=3.10
License-File: LICENSE.txt
Requires-Dist: Pillow (==10.2.0)
Requires-Dist: PyMuPDF (==1.23.20)
Requires-Dist: SQLAlchemy (==2.0.17)
Requires-Dist: boto3 (==1.18.44)
Requires-Dist: gensim (==4.3.1)
Requires-Dist: googletrans (==4.0.0rc1)
Requires-Dist: lingua-language-detector (==2.0.2)
Requires-Dist: lxml (==4.9.2)
Requires-Dist: nltk (==3.8.1)
Requires-Dist: numpy (==1.25.2)
Requires-Dist: ocrmypdf (==16.2.0)
Requires-Dist: opencv-python-headless (==4.8.0.74)
Requires-Dist: openpyxl (==3.0.10)
Requires-Dist: pandas (==2.0.3)
Requires-Dist: pyodbc (==4.0.35)
Requires-Dist: pyspellchecker (==0.8.1)
Requires-Dist: pytesseract (==0.3.10)
Requires-Dist: scipy (==1.11.1)
Requires-Dist: sentence-transformers (==2.2.2)
Requires-Dist: spacy (==3.6.0)
Requires-Dist: transformers (==4.33.3)
Provides-Extra: dev
Requires-Dist: Cython (==3.0.0) ; extra == 'dev'
Requires-Dist: flake8 (>=3.7) ; extra == 'dev'
Requires-Dist: pytest (>=5.1) ; extra == 'dev'
Provides-Extra: docs
Requires-Dist: sphinx ; extra == 'docs'
Requires-Dist: sphinx-rtd-theme ; extra == 'docs'
